fastapi_mongodb/__init__.py
fastapi_mongodb/config.py
fastapi_mongodb/db.py
fastapi_mongodb/dependencies.py
fastapi_mongodb/exceptions.py
fastapi_mongodb/helpers.py
fastapi_mongodb/logging.py
fastapi_mongodb/managers.py
fastapi_mongodb/middlewares.py
fastapi_mongodb/models.py
fastapi_mongodb/repositories.py
fastapi_mongodb/schemas.py
fastapi_mongodb/types.py
fastapi_mongodb-0.0.1b4.dist-info/LICENSE.MD
fastapi_mongodb-0.0.1b4.dist-info/WHEEL
fastapi_mongodb-0.0.1b4.dist-info/METADATA
fastapi_mongodb-0.0.1b4.dist-info/RECORD
