Metadata-Version: 2.1
Name: fastapi-mongodb
Version: 0.0.1b4
Summary: A library that simplifies work and integration with MongoDB for a FastAPI project.
Home-page: https://kostiantyn-salnykov.github.io/fastapi-mongodb/
License: MIT
Keywords: fastapi,mongodb,pydantic,motor,pymongo,orjson,pyjwt
Author: Kostiantyn Salnykov
Author-email: kostiantyn.salnykov@gmail.com
Maintainer: Kostiantyn Salnykov
Maintainer-email: kostiantyn.salnykov@gmail.com
Requires-Python: >=3.9,<4.0
Classifier: License :: OSI Approved :: MIT License
Classifier: Programming Language :: Python :: 3
Classifier: Programming Language :: Python :: 3.9
Classifier: Topic :: Software Development
Classifier: Topic :: Software Development :: Libraries
Classifier: Topic :: Software Development :: Libraries :: Python Modules
Provides-Extra: orjson
Requires-Dist: click (>=8.0.1,<9.0.0)
Requires-Dist: fastapi (>=0.68.1,<0.69.0)
Requires-Dist: motor (>=2.5.1,<3.0.0)
Requires-Dist: orjson (>=3.6.3,<4.0.0); extra == "orjson"
Requires-Dist: pydantic[email,dotenv] (>=1.8.2,<2.0.0)
Requires-Dist: pyjwt (>=2.1.0,<3.0.0)
Requires-Dist: pymongo[tls,srv] (>=3.12.0,<4.0.0)
Project-URL: Documentation, https://kostiantyn-salnykov.github.io/fastapi-mongodb/
Project-URL: Discussions, https://github.com/Kostiantyn-Salnykov/fastapi-mongodb/discussions
Project-URL: Issues, https://github.com/Kostiantyn-Salnykov/fastapi-mongodb/issues
Project-URL: Repository, https://github.com/Kostiantyn-Salnykov/fastapi-mongodb/
